explorer/__init__.py
explorer/admin.py
explorer/apps.py
explorer/tests.py
explorer/urls.py
explorer/migrations/__init__.py
explorer/models/__init__.py
explorer/models/action.py
explorer/models/user_role.py
explorer/models/volume.py
explorer/templates/explorer/base.html
explorer/templates/explorer/error.html
explorer/templates/explorer/index.html
explorer/views/__init__.py
explorer/views/main.py
explorer/views/utils/__init__.py
explorer/views/utils/operations.py
explorer/views/utils/request_validator.py
explorer/views/utils/sorting.py
test/myproject/manage.py
test/myproject/myproject/__init__.py
test/myproject/myproject/asgi.py
test/myproject/myproject/settings.py
test/myproject/myproject/urls.py
test/myproject/myproject/wsgi.py
djnago_file_explorer-0.0.2.dist-info/METADATA
djnago_file_explorer-0.0.2.dist-info/WHEEL
djnago_file_explorer-0.0.2.dist-info/top_level.txt
djnago_file_explorer-0.0.2.dist-info/RECORD
