Metadata-Version: 2.1
Name: djnago-file-explorer
Version: 0.0.2
Summary: Django app to explore directory.
Author: Tahir Rafique
Author-email: tahirrafiqueasad@gmail.com
License: MIT
Keywords: explorer,file explorer,directory explorer,django explorer,location explorer
Classifier: Framework :: Django :: 3.2
Classifier: Topic :: Software Development :: Libraries :: Python Modules
Classifier: Development Status :: 1 - Planning
Classifier: License :: OSI Approved :: MIT License
Classifier: Programming Language :: Python :: 3
Classifier: Programming Language :: Python :: 3.7
Classifier: Programming Language :: Python :: 3.8
Classifier: Operating System :: OS Independent
Classifier: Environment :: Web Environment
Classifier: Intended Audience :: Developers
Classifier: Intended Audience :: Science/Research
Classifier: Intended Audience :: Information Technology
Classifier: Natural Language :: English
Requires-Dist: requests
Requires-Dist: django (>=3.2.10)
